scimba-1.1.1.dist-info/licenses/LICENSE
scimba_torch/__init__.py
scimba_torch/approximation_space/__init__.py
scimba_torch/approximation_space/abstract_space.py
scimba_torch/approximation_space/kernelx_space.py
scimba_torch/approximation_space/nn_space.py
scimba_torch/approximation_space/radial_space.py
scimba_torch/approximation_space/spectral_space.py
scimba_torch/domain/__init__.py
scimba_torch/domain/sdf.py
scimba_torch/domain/mesh_based_domain/__init__.py
scimba_torch/domain/mesh_based_domain/cuboid.py
scimba_torch/domain/meshless_domain/__init__.py
scimba_torch/domain/meshless_domain/base.py
scimba_torch/domain/meshless_domain/domain_1d.py
scimba_torch/domain/meshless_domain/domain_2d.py
scimba_torch/domain/meshless_domain/domain_3d.py
scimba_torch/domain/meshless_domain/domain_nd.py
scimba_torch/flows/__init__.py
scimba_torch/flows/create_solution.py
scimba_torch/flows/deep_flows.py
scimba_torch/flows/discretization_based_flows.py
scimba_torch/flows/flow_trainer.py
scimba_torch/flows/integrators_ode.py
scimba_torch/geometry/__init__.py
scimba_torch/geometry/monte_carlo_hypersurface.py
scimba_torch/geometry/parametric_hypersurface.py
scimba_torch/geometry/regularized_eikonal_pde.py
scimba_torch/geometry/regularized_sdf_projectors.py
scimba_torch/geometry/utils.py
scimba_torch/integration/__init__.py
scimba_torch/integration/mesh_based_quadrature.py
scimba_torch/integration/monte_carlo.py
scimba_torch/integration/monte_carlo_parameters.py
scimba_torch/integration/monte_carlo_time.py
scimba_torch/neural_nets/__init__.py
scimba_torch/neural_nets/coordinates_based_nets/__init__.py
scimba_torch/neural_nets/coordinates_based_nets/activation.py
scimba_torch/neural_nets/coordinates_based_nets/discontinuous_mlp.py
scimba_torch/neural_nets/coordinates_based_nets/features.py
scimba_torch/neural_nets/coordinates_based_nets/mlp.py
scimba_torch/neural_nets/coordinates_based_nets/pirate_net.py
scimba_torch/neural_nets/coordinates_based_nets/res_net.py
scimba-1.1.1.dist-info/METADATA
scimba-1.1.1.dist-info/WHEEL
scimba-1.1.1.dist-info/top_level.txt
scimba-1.1.1.dist-info/RECORD
