Metadata-Version: 2.4
Name: scimba
Version: 1.1.1
Summary: This library implements some common tools for scientific machine learning
Author-email: Emmanuel Franck <emmanuel.franck@inria.fr>, Rémi Imbach <remi.imbach@inria.fr>, Victor Michel-Dansac <victor.michel-dansac@inria.fr>
Maintainer-email: Matthieu Boileau <matthieu.boileau@math.unistra.fr>, Rémi Imbach <remi.imbach@inria.fr>
License: MIT
Project-URL: Homepage, https://www.scimba.org
Project-URL: Documentation, https://www.scimba.org
Project-URL: Repository, https://gitlab.com/scimba/scimba.git
Project-URL: Issues, https://gitlab.com/scimba/scimba/-/issues
Project-URL: Changelog, https://gitlab.com/scimba/scimba/-/blob/main/CHANGELOG.md
Classifier: Programming Language :: Python :: 3
Classifier: License :: OSI Approved :: MIT License
Classifier: Operating System :: OS Independent
Requires-Python: >=3.10
License-File: LICENSE
Requires-Dist: matplotlib
Requires-Dist: numpy
Requires-Dist: torch>=2.9
Requires-Dist: scipy
Requires-Dist: tqdm
Dynamic: license-file
